glogger/__init__.py
glogger/main.py
glogger/base/__init__.py
glogger/base/client.py
glogger/base/logger.py
glogger/cli/__init__.py
glogger/cli/command.py
glogger/config/__init__.py
glogger/config/environment.py
glogger/providers/__init__.py
glogger/providers/aws/__init__.py
glogger/providers/aws/cloudwatch.py
glogger/providers/aws/s3.py
glogger/providers/azure/__init__.py
glogger/providers/azure/blob.py
glogger/providers/azure/insight.py
glogger/providers/google/__init__.py
glogger/providers/google/logging.py
glogger/providers/google/storage.py
glogger/providers/local/__init__.py
glogger/providers/local/file.py
glogger/providers/socket/__init__.py
glogger/providers/socket/papertrail.py
glogger/providers/socket/websocket.py
gfrancodev_glogger-0.3.10.dist-info/LICENSE
gfrancodev_glogger-0.3.10.dist-info/METADATA
gfrancodev_glogger-0.3.10.dist-info/WHEEL
gfrancodev_glogger-0.3.10.dist-info/entry_points.txt
gfrancodev_glogger-0.3.10.dist-info/top_level.txt
gfrancodev_glogger-0.3.10.dist-info/RECORD
